fight_detection/Fight_utils.py
fight_detection/__init__.py
Fight_Detection-0.0.8.dist-info/LICENCE
Fight_Detection-0.0.8.dist-info/METADATA
Fight_Detection-0.0.8.dist-info/WHEEL
Fight_Detection-0.0.8.dist-info/top_level.txt
Fight_Detection-0.0.8.dist-info/RECORD
