Metadata-Version: 2.1
Name: Fight-Detection
Version: 0.0.8
Summary: Detect Fight From Surveillance Cameras and Video Streams
Home-page: https://github.com/MohamedSebaie/Fight_Detection_From_Surveillance_Cameras-PyTorch_Project
Author: The Innovators
Author-email: mohamedsebaie1@gmail.com
License: UNKNOWN
Platform: UNKNOWN
Classifier: Programming Language :: Python :: 3
Classifier: License :: OSI Approved :: MIT License
Classifier: Operating System :: OS Independent
Requires-Python: >=3.7
License-File: LICENCE
